MANIFEST.in
requirements.txt
setup.py
servers/__init__.py
servers/servers.py
servers.py.egg-info/PKG-INFO
servers.py.egg-info/SOURCES.txt
servers.py.egg-info/dependency_links.txt
servers.py.egg-info/not-zip-safe
servers.py.egg-info/requires.txt
servers.py.egg-info/top_level.txt
servers/skeletons/nginx/base.conf
servers/skeletons/nginx/ssl.conf
servers/skeletons/nginx/applications/django.conf
servers/skeletons/nginx/applications/php.conf
servers/skeletons/nginx/applications/static.conf
servers/skeletons/nginx/applications/wordpress.conf
servers/skeletons/uwsgi/base.ini
servers/skeletons/uwsgi/gevent.ini
servers/skeletons/uwsgi/applications/django.ini