Metadata-Version: 1.1
Name: servers.py
Version: 0.1.7
Summary: Config generation library.
Home-page: https://github.com/radiosilence/servers.py
Author: James Cleveland
Author-email: james@dapperdogstudios.com
License: UNKNOWN
Platform: UNKNOWN
Classifier: Environment :: Web Environment
Classifier: Intended Audience :: Developers
Classifier: License :: OSI Approved :: BSD License
Classifier: Operating System :: OS Independent
Classifier: Programming Language :: Python
